{
  "_note": "全塔切层事件清单（共 220 次）。type: changeFloor=楼梯（途中可能有 Mn:/ITEM 噪声）, centerFly=ITEM:50+CHOICE, keyboard_fly=K49/K50/K52 快捷键, unknown_p=UNK:p前驱（待查）。",
  "total_transitions": 220,
  "type_counts": {
    "changeFloor": 217,
    "centerFly": 1,
    "keyboard_fly": 2
  },
  "multi_visit_floors": {
    "MT4": 8,
    "MT5": 4,
    "MT8": 7,
    "MT7": 6,
    "MT3": 4,
    "MT1": 9,
    "MT9": 5,
    "MT6": 6,
    "MT10": 4,
    "MT11": 6,
    "MT15": 7,
    "MT16": 4,
    "MT17": 8,
    "MT14": 8,
    "MT18": 4,
    "MT19": 5,
    "MT12": 4,
    "MT20": 9,
    "MT32": 9,
    "MT33": 5,
    "MT31": 11,
    "MT34": 6,
    "MT2": 3,
    "MT35": 4,
    "MT36": 3,
    "MT37": 3,
    "MT38": 5,
    "MT39": 4,
    "MT40": 5,
    "MT42": 5,
    "MT43": 5,
    "MT46": 8,
    "MT45": 9,
    "MT48": 5,
    "MT47": 6,
    "MT41": 8,
    "MT49": 3,
    "MT25": 2
  },
  "anomalies": [],
  "type_examples": {
    "changeFloor": {
      "seq": 0,
      "global_idx": 186,
      "from_floor": null,
      "to_floor": "MT4",
      "waste": 30,
      "trigger": null,
      "context_before_last15": [
        "L",
        "D",
        "D",
        "D",
        "D",
        "D",
        "R",
        "R",
        "R",
        "R",
        "L",
        "L",
        "L",
        "L",
        "L"
      ],
      "context_after_10": [
        "U",
        "U",
        "U",
        "R",
        "R",
        "R",
        "R",
        "R",
        "R",
        "R"
      ]
    },
    "centerFly": {
      "seq": 148,
      "global_idx": 4368,
      "from_floor": "MT46",
      "to_floor": "MT37",
      "waste": 15,
      "trigger": "ITEM:50",
      "context_before_last15": [
        "R",
        "R",
        "R",
        "D",
        "D",
        "D",
        "R",
        "CHOICE:0",
        "R",
        "U",
        "U",
        "U",
        "L",
        "L",
        "L"
      ],
      "context_after_10": [
        "UNK:K52",
        "R",
        "R",
        "L",
        "L",
        "D",
        "D",
        "D",
        "D",
        "R"
      ]
    },
    "keyboard_fly": {
      "seq": 151,
      "global_idx": 4534,
      "from_floor": "MT45",
      "to_floor": "MT37",
      "waste": 9,
      "trigger": "UNK:K50",
      "context_before_last15": [
        "L",
        "U",
        "U",
        "U",
        "U",
        "UNK:K50",
        "U",
        "U",
        "U",
        "U",
        "D",
        "L",
        "L",
        "R",
        "R"
      ],
      "context_after_10": [
        "R",
        "D",
        "D",
        "D",
        "R",
        "U",
        "R",
        "R",
        "R",
        "D"
      ]
    }
  },
  "transitions": [
    {
      "seq": 0,
      "global_idx": 186,
      "from_floor": null,
      "to_floor": "MT4",
      "type": "changeFloor",
      "trigger_token": null,
      "waste": 30
    },
    {
      "seq": 1,
      "global_idx": 210,
      "from_floor": "MT4",
      "to_floor": "MT5",
      "type": "changeFloor",
      "trigger_token": null,
      "waste": 23
    },
    {
      "seq": 2,
      "global_idx": 256,
      "from_floor": "MT5",
      "to_floor": "MT4",
      "type": "changeFloor",
      "trigger_token": null,
      "waste": 30
    },
    {
      "seq": 3,
      "global_idx": 280,
      "from_floor": "MT4",
      "to_floor": "MT5",
      "type": "changeFloor",
      "trigger_token": null,
      "waste": 23
    },
    {
      "seq": 4,
      "global_idx": 546,
      "from_floor": "MT5",
      "to_floor": "MT8",
      "type": "changeFloor",
      "trigger_token": null,
      "waste": 30
    },
    {
      "seq": 5,
      "global_idx": 547,
      "from_floor": "MT8",
      "to_floor": "MT7",
      "type": "changeFloor",
      "trigger_token": null,
      "waste": 0
    },
    {
      "seq": 6,
      "global_idx": 573,
      "from_floor": "MT7",
      "to_floor": "MT3",
      "type": "changeFloor",
      "trigger_token": null,
      "waste": 25
    },
    {
      "seq": 7,
      "global_idx": 611,
      "from_floor": "MT3",
      "to_floor": "MT7",
      "type": "changeFloor",
      "trigger_token": null,
      "waste": 30
    },
    {
      "seq": 8,
      "global_idx": 624,
      "from_floor": "MT7",
      "to_floor": "MT1",
      "type": "changeFloor",
      "trigger_token": null,
      "waste": 12
    },
    {
      "seq": 9,
      "global_idx": 672,
      "from_floor": "MT1",
      "to_floor": "MT8",
      "type": "changeFloor",
      "trigger_token": null,
      "waste": 30
    },
    {
      "seq": 10,
      "global_idx": 713,
      "from_floor": "MT8",
      "to_floor": "MT4",
      "type": "changeFloor",
      "trigger_token": null,
      "waste": 30
    },
    {
      "seq": 11,
      "global_idx": 733,
      "from_floor": "MT4",
      "to_floor": "MT9",
      "type": "changeFloor",
      "trigger_token": null,
      "waste": 19
    },
    {
      "seq": 12,
      "global_idx": 803,
      "from_floor": "MT9",
      "to_floor": "MT1",
      "type": "changeFloor",
      "trigger_token": null,
      "waste": 30
    },
    {
      "seq": 13,
      "global_idx": 804,
      "from_floor": "MT1",
      "to_floor": "MT5",
      "type": "changeFloor",
      "trigger_token": null,
      "waste": 0
    },
    {
      "seq": 14,
      "global_idx": 844,
      "from_floor": "MT5",
      "to_floor": "MT6",
      "type": "changeFloor",
      "trigger_token": null,
      "waste": 30
    },
    {
      "seq": 15,
      "global_idx": 845,
      "from_floor": "MT6",
      "to_floor": "MT10",
      "type": "changeFloor",
      "trigger_token": null,
      "waste": 0
    },
    {
      "seq": 16,
      "global_idx": 846,
      "from_floor": "MT10",
      "to_floor": "MT6",
      "type": "changeFloor",
      "trigger_token": null,
      "waste": 0
    },
    {
      "seq": 17,
      "global_idx": 895,
      "from_floor": "MT6",
      "to_floor": "MT1",
      "type": "changeFloor",
      "trigger_token": null,
      "waste": 30
    },
    {
      "seq": 18,
      "global_idx": 896,
      "from_floor": "MT1",
      "to_floor": "MT7",
      "type": "changeFloor",
      "trigger_token": null,
      "waste": 0
    },
    {
      "seq": 19,
      "global_idx": 934,
      "from_floor": "MT7",
      "to_floor": "MT10",
      "type": "changeFloor",
      "trigger_token": null,
      "waste": 30
    },
    {
      "seq": 20,
      "global_idx": 959,
      "from_floor": "MT10",
      "to_floor": "MT1",
      "type": "changeFloor",
      "trigger_token": null,
      "waste": 24
    },
    {
      "seq": 21,
      "global_idx": 960,
      "from_floor": "MT1",
      "to_floor": "MT6",
      "type": "changeFloor",
      "trigger_token": null,
      "waste": 0
    },
    {
      "seq": 22,
      "global_idx": 980,
      "from_floor": "MT6",
      "to_floor": "MT10",
      "type": "changeFloor",
      "trigger_token": null,
      "waste": 19
    },
    {
      "seq": 23,
      "global_idx": 1009,
      "from_floor": "MT10",
      "to_floor": "MT8",
      "type": "changeFloor",
      "trigger_token": null,
      "waste": 28
    },
    {
      "seq": 24,
      "global_idx": 1043,
      "from_floor": "MT8",
      "to_floor": "MT7",
      "type": "changeFloor",
      "trigger_token": null,
      "waste": 30
    },
    {
      "seq": 25,
      "global_idx": 1090,
      "from_floor": "MT7",
      "to_floor": "MT1",
      "type": "changeFloor",
      "trigger_token": null,
      "waste": 30
    },
    {
      "seq": 26,
      "global_idx": 1127,
      "from_floor": "MT1",
      "to_floor": "MT3",
      "type": "changeFloor",
      "trigger_token": null,
      "waste": 30
    },
    {
      "seq": 27,
      "global_idx": 1129,
      "from_floor": "MT3",
      "to_floor": "MT4",
      "type": "changeFloor",
      "trigger_token": null,
      "waste": 1
    },
    {
      "seq": 28,
      "global_idx": 1141,
      "from_floor": "MT4",
      "to_floor": "MT1",
      "type": "changeFloor",
      "trigger_token": null,
      "waste": 11
    },
    {
      "seq": 29,
      "global_idx": 1168,
      "from_floor": "MT1",
      "to_floor": "MT10",
      "type": "changeFloor",
      "trigger_token": null,
      "waste": 26
    },
    {
      "seq": 30,
      "global_idx": 1317,
      "from_floor": "MT10",
      "to_floor": "MT11",
      "type": "changeFloor",
      "trigger_token": null,
      "waste": 30
    },
    {
      "seq": 31,
      "global_idx": 1333,
      "from_floor": "MT11",
      "to_floor": "MT15",
      "type": "changeFloor",
      "trigger_token": null,
      "waste": 15
    },
    {
      "seq": 32,
      "global_idx": 1378,
      "from_floor": "MT15",
      "to_floor": "MT8",
      "type": "changeFloor",
      "trigger_token": null,
      "waste": 30
    },
    {
      "seq": 33,
      "global_idx": 1384,
      "from_floor": "MT8",
      "to_floor": "MT6",
      "type": "changeFloor",
      "trigger_token": null,
      "waste": 5
    },
    {
      "seq": 34,
      "global_idx": 1416,
      "from_floor": "MT6",
      "to_floor": "MT16",
      "type": "changeFloor",
      "trigger_token": null,
      "waste": 30
    },
    {
      "seq": 35,
      "global_idx": 1499,
      "from_floor": "MT16",
      "to_floor": "MT1",
      "type": "changeFloor",
      "trigger_token": null,
      "waste": 30
    },
    {
      "seq": 36,
      "global_idx": 1500,
      "from_floor": "MT1",
      "to_floor": "MT3",
      "type": "changeFloor",
      "trigger_token": null,
      "waste": 0
    },
    {
      "seq": 37,
      "global_idx": 1503,
      "from_floor": "MT3",
      "to_floor": "MT4",
      "type": "changeFloor",
      "trigger_token": null,
      "waste": 2
    },
    {
      "seq": 38,
      "global_idx": 1518,
      "from_floor": "MT4",
      "to_floor": "MT7",
      "type": "changeFloor",
      "trigger_token": null,
      "waste": 14
    },
    {
      "seq": 39,
      "global_idx": 1536,
      "from_floor": "MT7",
      "to_floor": "MT17",
      "type": "changeFloor",
      "trigger_token": null,
      "waste": 17
    },
    {
      "seq": 40,
      "global_idx": 1537,
      "from_floor": "MT17",
      "to_floor": "MT8",
      "type": "changeFloor",
      "trigger_token": null,
      "waste": 0
    },
    {
      "seq": 41,
      "global_idx": 1567,
      "from_floor": "MT8",
      "to_floor": "MT17",
      "type": "changeFloor",
      "trigger_token": null,
      "waste": 29
    },
    {
      "seq": 42,
      "global_idx": 1568,
      "from_floor": "MT17",
      "to_floor": "MT11",
      "type": "changeFloor",
      "trigger_token": null,
      "waste": 0
    },
    {
      "seq": 43,
      "global_idx": 1671,
      "from_floor": "MT11",
      "to_floor": "MT11",
      "type": "changeFloor",
      "trigger_token": null,
      "waste": 30
    },
    {
      "seq": 44,
      "global_idx": 1731,
      "from_floor": "MT11",
      "to_floor": "MT17",
      "type": "changeFloor",
      "trigger_token": null,
      "waste": 30
    },
    {
      "seq": 45,
      "global_idx": 1804,
      "from_floor": "MT17",
      "to_floor": "MT16",
      "type": "changeFloor",
      "trigger_token": null,
      "waste": 30
    },
    {
      "seq": 46,
      "global_idx": 1805,
      "from_floor": "MT16",
      "to_floor": "MT15",
      "type": "changeFloor",
      "trigger_token": null,
      "waste": 0
    },
    {
      "seq": 47,
      "global_idx": 1806,
      "from_floor": "MT15",
      "to_floor": "MT14",
      "type": "changeFloor",
      "trigger_token": null,
      "waste": 0
    },
    {
      "seq": 48,
      "global_idx": 1807,
      "from_floor": "MT14",
      "to_floor": "MT15",
      "type": "changeFloor",
      "trigger_token": null,
      "waste": 0
    },
    {
      "seq": 49,
      "global_idx": 1817,
      "from_floor": "MT15",
      "to_floor": "MT18",
      "type": "changeFloor",
      "trigger_token": null,
      "waste": 9
    },
    {
      "seq": 50,
      "global_idx": 1825,
      "from_floor": "MT18",
      "to_floor": "MT19",
      "type": "changeFloor",
      "trigger_token": null,
      "waste": 7
    },
    {
      "seq": 51,
      "global_idx": 1826,
      "from_floor": "MT19",
      "to_floor": "MT18",
      "type": "changeFloor",
      "trigger_token": null,
      "waste": 0
    },
    {
      "seq": 52,
      "global_idx": 1850,
      "from_floor": "MT18",
      "to_floor": "MT12",
      "type": "changeFloor",
      "trigger_token": null,
      "waste": 23
    },
    {
      "seq": 53,
      "global_idx": 1857,
      "from_floor": "MT12",
      "to_floor": "MT11",
      "type": "changeFloor",
      "trigger_token": null,
      "waste": 6
    },
    {
      "seq": 54,
      "global_idx": 1875,
      "from_floor": "MT11",
      "to_floor": "MT19",
      "type": "changeFloor",
      "trigger_token": null,
      "waste": 17
    },
    {
      "seq": 55,
      "global_idx": 1982,
      "from_floor": "MT19",
      "to_floor": "MT18",
      "type": "changeFloor",
      "trigger_token": null,
      "waste": 30
    },
    {
      "seq": 56,
      "global_idx": 1983,
      "from_floor": "MT18",
      "to_floor": "MT17",
      "type": "changeFloor",
      "trigger_token": null,
      "waste": 0
    },
    {
      "seq": 57,
      "global_idx": 1984,
      "from_floor": "MT17",
      "to_floor": "MT16",
      "type": "changeFloor",
      "trigger_token": null,
      "waste": 0
    },
    {
      "seq": 58,
      "global_idx": 2050,
      "from_floor": "MT16",
      "to_floor": "MT20",
      "type": "changeFloor",
      "trigger_token": null,
      "waste": 30
    },
    {
      "seq": 59,
      "global_idx": 2051,
      "from_floor": "MT20",
      "to_floor": "MT19",
      "type": "changeFloor",
      "trigger_token": null,
      "waste": 0
    },
    {
      "seq": 60,
      "global_idx": 2098,
      "from_floor": "MT19",
      "to_floor": "MT17",
      "type": "changeFloor",
      "trigger_token": null,
      "waste": 30
    },
    {
      "seq": 61,
      "global_idx": 2099,
      "from_floor": "MT17",
      "to_floor": "MT16",
      "type": "changeFloor",
      "trigger_token": null,
      "waste": 0
    },
    {
      "seq": 62,
      "global_idx": 2100,
      "from_floor": "MT16",
      "to_floor": "MT15",
      "type": "changeFloor",
      "trigger_token": null,
      "waste": 0
    },
    {
      "seq": 63,
      "global_idx": 2113,
      "from_floor": "MT15",
      "to_floor": "MT14",
      "type": "changeFloor",
      "trigger_token": null,
      "waste": 12
    },
    {
      "seq": 64,
      "global_idx": 2127,
      "from_floor": "MT14",
      "to_floor": "MT12",
      "type": "changeFloor",
      "trigger_token": null,
      "waste": 13
    },
    {
      "seq": 65,
      "global_idx": 2141,
      "from_floor": "MT12",
      "to_floor": "MT14",
      "type": "changeFloor",
      "trigger_token": null,
      "waste": 13
    },
    {
      "seq": 66,
      "global_idx": 2175,
      "from_floor": "MT14",
      "to_floor": "MT11",
      "type": "changeFloor",
      "trigger_token": null,
      "waste": 30
    },
    {
      "seq": 67,
      "global_idx": 2176,
      "from_floor": "MT11",
      "to_floor": "MT9",
      "type": "changeFloor",
      "trigger_token": null,
      "waste": 0
    },
    {
      "seq": 68,
      "global_idx": 2198,
      "from_floor": "MT9",
      "to_floor": "MT8",
      "type": "changeFloor",
      "trigger_token": null,
      "waste": 21
    },
    {
      "seq": 69,
      "global_idx": 2199,
      "from_floor": "MT8",
      "to_floor": "MT6",
      "type": "changeFloor",
      "trigger_token": null,
      "waste": 0
    },
    {
      "seq": 70,
      "global_idx": 2202,
      "from_floor": "MT6",
      "to_floor": "MT4",
      "type": "changeFloor",
      "trigger_token": null,
      "waste": 2
    },
    {
      "seq": 71,
      "global_idx": 2203,
      "from_floor": "MT4",
      "to_floor": "MT1",
      "type": "changeFloor",
      "trigger_token": null,
      "waste": 0
    },
    {
      "seq": 72,
      "global_idx": 2277,
      "from_floor": "MT1",
      "to_floor": "MT20",
      "type": "changeFloor",
      "trigger_token": null,
      "waste": 30
    },
    {
      "seq": 73,
      "global_idx": 2278,
      "from_floor": "MT20",
      "to_floor": "MT15",
      "type": "changeFloor",
      "trigger_token": null,
      "waste": 0
    },
    {
      "seq": 74,
      "global_idx": 2295,
      "from_floor": "MT15",
      "to_floor": "MT20",
      "type": "changeFloor",
      "trigger_token": null,
      "waste": 16
    },
    {
      "seq": 75,
      "global_idx": 2296,
      "from_floor": "MT20",
      "to_floor": "MT20",
      "type": "changeFloor",
      "trigger_token": null,
      "waste": 0
    },
    {
      "seq": 76,
      "global_idx": 2299,
      "from_floor": "MT20",
      "to_floor": "MT11",
      "type": "changeFloor",
      "trigger_token": null,
      "waste": 2
    },
    {
      "seq": 77,
      "global_idx": 2322,
      "from_floor": "MT11",
      "to_floor": "MT20",
      "type": "changeFloor",
      "trigger_token": null,
      "waste": 22
    },
    {
      "seq": 78,
      "global_idx": 2503,
      "from_floor": "MT20",
      "to_floor": "MT12",
      "type": "changeFloor",
      "trigger_token": null,
      "waste": 30
    },
    {
      "seq": 79,
      "global_idx": 2511,
      "from_floor": "MT12",
      "to_floor": "MT9",
      "type": "changeFloor",
      "trigger_token": null,
      "waste": 7
    },
    {
      "seq": 80,
      "global_idx": 2512,
      "from_floor": "MT9",
      "to_floor": "MT9",
      "type": "changeFloor",
      "trigger_token": null,
      "waste": 0
    },
    {
      "seq": 81,
      "global_idx": 2522,
      "from_floor": "MT9",
      "to_floor": "MT17",
      "type": "changeFloor",
      "trigger_token": null,
      "waste": 9
    },
    {
      "seq": 82,
      "global_idx": 2528,
      "from_floor": "MT17",
      "to_floor": "MT17",
      "type": "changeFloor",
      "trigger_token": null,
      "waste": 5
    },
    {
      "seq": 83,
      "global_idx": 2529,
      "from_floor": "MT17",
      "to_floor": "MT15",
      "type": "changeFloor",
      "trigger_token": null,
      "waste": 0
    },
    {
      "seq": 84,
      "global_idx": 2530,
      "from_floor": "MT15",
      "to_floor": "MT14",
      "type": "changeFloor",
      "trigger_token": null,
      "waste": 0
    },
    {
      "seq": 85,
      "global_idx": 2531,
      "from_floor": "MT14",
      "to_floor": "MT14",
      "type": "changeFloor",
      "trigger_token": null,
      "waste": 0
    },
    {
      "seq": 86,
      "global_idx": 2544,
      "from_floor": "MT14",
      "to_floor": "MT32",
      "type": "changeFloor",
      "trigger_token": null,
      "waste": 12
    },
    {
      "seq": 87,
      "global_idx": 2565,
      "from_floor": "MT32",
      "to_floor": "MT17",
      "type": "changeFloor",
      "trigger_token": null,
      "waste": 20
    },
    {
      "seq": 88,
      "global_idx": 2631,
      "from_floor": "MT17",
      "to_floor": "MT32",
      "type": "changeFloor",
      "trigger_token": null,
      "waste": 30
    },
    {
      "seq": 89,
      "global_idx": 2697,
      "from_floor": "MT32",
      "to_floor": "MT15",
      "type": "changeFloor",
      "trigger_token": null,
      "waste": 30
    },
    {
      "seq": 90,
      "global_idx": 2729,
      "from_floor": "MT15",
      "to_floor": "MT33",
      "type": "changeFloor",
      "trigger_token": null,
      "waste": 30
    },
    {
      "seq": 91,
      "global_idx": 2806,
      "from_floor": "MT33",
      "to_floor": "MT20",
      "type": "changeFloor",
      "trigger_token": null,
      "waste": 30
    },
    {
      "seq": 92,
      "global_idx": 2807,
      "from_floor": "MT20",
      "to_floor": "MT33",
      "type": "changeFloor",
      "trigger_token": null,
      "waste": 0
    },
    {
      "seq": 93,
      "global_idx": 2808,
      "from_floor": "MT33",
      "to_floor": "MT32",
      "type": "changeFloor",
      "trigger_token": null,
      "waste": 0
    },
    {
      "seq": 94,
      "global_idx": 2809,
      "from_floor": "MT32",
      "to_floor": "MT31",
      "type": "changeFloor",
      "trigger_token": null,
      "waste": 0
    },
    {
      "seq": 95,
      "global_idx": 2810,
      "from_floor": "MT31",
      "to_floor": "MT14",
      "type": "changeFloor",
      "trigger_token": null,
      "waste": 0
    },
    {
      "seq": 96,
      "global_idx": 2832,
      "from_floor": "MT14",
      "to_floor": "MT18",
      "type": "changeFloor",
      "trigger_token": null,
      "waste": 21
    },
    {
      "seq": 97,
      "global_idx": 2891,
      "from_floor": "MT18",
      "to_floor": "MT33",
      "type": "changeFloor",
      "trigger_token": null,
      "waste": 30
    },
    {
      "seq": 98,
      "global_idx": 2973,
      "from_floor": "MT33",
      "to_floor": "MT20",
      "type": "changeFloor",
      "trigger_token": null,
      "waste": 30
    },
    {
      "seq": 99,
      "global_idx": 3001,
      "from_floor": "MT20",
      "to_floor": "MT14",
      "type": "changeFloor",
      "trigger_token": null,
      "waste": 27
    },
    {
      "seq": 100,
      "global_idx": 3025,
      "from_floor": "MT14",
      "to_floor": "MT33",
      "type": "changeFloor",
      "trigger_token": null,
      "waste": 23
    },
    {
      "seq": 101,
      "global_idx": 3026,
      "from_floor": "MT33",
      "to_floor": "MT33",
      "type": "changeFloor",
      "trigger_token": null,
      "waste": 0
    },
    {
      "seq": 102,
      "global_idx": 3090,
      "from_floor": "MT33",
      "to_floor": "MT31",
      "type": "changeFloor",
      "trigger_token": null,
      "waste": 30
    },
    {
      "seq": 103,
      "global_idx": 3091,
      "from_floor": "MT31",
      "to_floor": "MT14",
      "type": "changeFloor",
      "trigger_token": null,
      "waste": 0
    },
    {
      "seq": 104,
      "global_idx": 3133,
      "from_floor": "MT14",
      "to_floor": "MT34",
      "type": "changeFloor",
      "trigger_token": null,
      "waste": 30
    },
    {
      "seq": 105,
      "global_idx": 3171,
      "from_floor": "MT34",
      "to_floor": "MT2",
      "type": "changeFloor",
      "trigger_token": null,
      "waste": 30
    },
    {
      "seq": 106,
      "global_idx": 3172,
      "from_floor": "MT2",
      "to_floor": "MT19",
      "type": "changeFloor",
      "trigger_token": null,
      "waste": 0
    },
    {
      "seq": 107,
      "global_idx": 3212,
      "from_floor": "MT19",
      "to_floor": "MT2",
      "type": "changeFloor",
      "trigger_token": null,
      "waste": 30
    },
    {
      "seq": 108,
      "global_idx": 3276,
      "from_floor": "MT2",
      "to_floor": "MT32",
      "type": "changeFloor",
      "trigger_token": null,
      "waste": 30
    },
    {
      "seq": 109,
      "global_idx": 3279,
      "from_floor": "MT32",
      "to_floor": "MT35",
      "type": "changeFloor",
      "trigger_token": null,
      "waste": 2
    },
    {
      "seq": 110,
      "global_idx": 3329,
      "from_floor": "MT35",
      "to_floor": "MT34",
      "type": "changeFloor",
      "trigger_token": null,
      "waste": 30
    },
    {
      "seq": 111,
      "global_idx": 3343,
      "from_floor": "MT34",
      "to_floor": "MT32",
      "type": "changeFloor",
      "trigger_token": null,
      "waste": 13
    },
    {
      "seq": 112,
      "global_idx": 3387,
      "from_floor": "MT32",
      "to_floor": "MT36",
      "type": "changeFloor",
      "trigger_token": null,
      "waste": 30
    },
    {
      "seq": 113,
      "global_idx": 3401,
      "from_floor": "MT36",
      "to_floor": "MT32",
      "type": "changeFloor",
      "trigger_token": null,
      "waste": 13
    },
    {
      "seq": 114,
      "global_idx": 3444,
      "from_floor": "MT32",
      "to_floor": "MT37",
      "type": "changeFloor",
      "trigger_token": null,
      "waste": 30
    },
    {
      "seq": 115,
      "global_idx": 3468,
      "from_floor": "MT37",
      "to_floor": "MT34",
      "type": "changeFloor",
      "trigger_token": null,
      "waste": 23
    },
    {
      "seq": 116,
      "global_idx": 3469,
      "from_floor": "MT34",
      "to_floor": "MT32",
      "type": "changeFloor",
      "trigger_token": null,
      "waste": 0
    },
    {
      "seq": 117,
      "global_idx": 3526,
      "from_floor": "MT32",
      "to_floor": "MT31",
      "type": "changeFloor",
      "trigger_token": null,
      "waste": 30
    },
    {
      "seq": 118,
      "global_idx": 3573,
      "from_floor": "MT31",
      "to_floor": "MT34",
      "type": "changeFloor",
      "trigger_token": null,
      "waste": 30
    },
    {
      "seq": 119,
      "global_idx": 3574,
      "from_floor": "MT34",
      "to_floor": "MT31",
      "type": "changeFloor",
      "trigger_token": null,
      "waste": 0
    },
    {
      "seq": 120,
      "global_idx": 3595,
      "from_floor": "MT31",
      "to_floor": "MT38",
      "type": "changeFloor",
      "trigger_token": null,
      "waste": 20
    },
    {
      "seq": 121,
      "global_idx": 3597,
      "from_floor": "MT38",
      "to_floor": "MT35",
      "type": "changeFloor",
      "trigger_token": null,
      "waste": 1
    },
    {
      "seq": 122,
      "global_idx": 3598,
      "from_floor": "MT35",
      "to_floor": "MT34",
      "type": "changeFloor",
      "trigger_token": null,
      "waste": 0
    },
    {
      "seq": 123,
      "global_idx": 3704,
      "from_floor": "MT34",
      "to_floor": "MT38",
      "type": "changeFloor",
      "trigger_token": null,
      "waste": 30
    },
    {
      "seq": 124,
      "global_idx": 3820,
      "from_floor": "MT38",
      "to_floor": "MT31",
      "type": "changeFloor",
      "trigger_token": null,
      "waste": 30
    },
    {
      "seq": 125,
      "global_idx": 3845,
      "from_floor": "MT31",
      "to_floor": "MT39",
      "type": "changeFloor",
      "trigger_token": null,
      "waste": 24
    },
    {
      "seq": 126,
      "global_idx": 3926,
      "from_floor": "MT39",
      "to_floor": "MT39",
      "type": "changeFloor",
      "trigger_token": null,
      "waste": 30
    },
    {
      "seq": 127,
      "global_idx": 3951,
      "from_floor": "MT39",
      "to_floor": "MT38",
      "type": "changeFloor",
      "trigger_token": null,
      "waste": 24
    },
    {
      "seq": 128,
      "global_idx": 3952,
      "from_floor": "MT38",
      "to_floor": "MT36",
      "type": "changeFloor",
      "trigger_token": null,
      "waste": 0
    },
    {
      "seq": 129,
      "global_idx": 3963,
      "from_floor": "MT36",
      "to_floor": "MT31",
      "type": "changeFloor",
      "trigger_token": null,
      "waste": 10
    },
    {
      "seq": 130,
      "global_idx": 3994,
      "from_floor": "MT31",
      "to_floor": "MT40",
      "type": "changeFloor",
      "trigger_token": null,
      "waste": 30
    },
    {
      "seq": 131,
      "global_idx": 4014,
      "from_floor": "MT40",
      "to_floor": "MT38",
      "type": "changeFloor",
      "trigger_token": null,
      "waste": 19
    },
    {
      "seq": 132,
      "global_idx": 4037,
      "from_floor": "MT38",
      "to_floor": "MT39",
      "type": "changeFloor",
      "trigger_token": null,
      "waste": 22
    },
    {
      "seq": 133,
      "global_idx": 4064,
      "from_floor": "MT39",
      "to_floor": "MT36",
      "type": "changeFloor",
      "trigger_token": null,
      "waste": 26
    },
    {
      "seq": 134,
      "global_idx": 4084,
      "from_floor": "MT36",
      "to_floor": "MT40",
      "type": "changeFloor",
      "trigger_token": null,
      "waste": 19
    },
    {
      "seq": 135,
      "global_idx": 4156,
      "from_floor": "MT40",
      "to_floor": "MT40",
      "type": "changeFloor",
      "trigger_token": null,
      "waste": 30
    },
    {
      "seq": 136,
      "global_idx": 4163,
      "from_floor": "MT40",
      "to_floor": "MT42",
      "type": "changeFloor",
      "trigger_token": null,
      "waste": 6
    },
    {
      "seq": 137,
      "global_idx": 4187,
      "from_floor": "MT42",
      "to_floor": "MT40",
      "type": "changeFloor",
      "trigger_token": null,
      "waste": 23
    },
    {
      "seq": 138,
      "global_idx": 4193,
      "from_floor": "MT40",
      "to_floor": "MT32",
      "type": "changeFloor",
      "trigger_token": null,
      "waste": 5
    },
    {
      "seq": 139,
      "global_idx": 4194,
      "from_floor": "MT32",
      "to_floor": "MT31",
      "type": "changeFloor",
      "trigger_token": null,
      "waste": 0
    },
    {
      "seq": 140,
      "global_idx": 4204,
      "from_floor": "MT31",
      "to_floor": "MT32",
      "type": "changeFloor",
      "trigger_token": null,
      "waste": 9
    },
    {
      "seq": 141,
      "global_idx": 4231,
      "from_floor": "MT32",
      "to_floor": "MT31",
      "type": "changeFloor",
      "trigger_token": null,
      "waste": 26
    },
    {
      "seq": 142,
      "global_idx": 4256,
      "from_floor": "MT31",
      "to_floor": "MT34",
      "type": "changeFloor",
      "trigger_token": null,
      "waste": 24
    },
    {
      "seq": 143,
      "global_idx": 4291,
      "from_floor": "MT34",
      "to_floor": "MT43",
      "type": "changeFloor",
      "trigger_token": null,
      "waste": 30
    },
    {
      "seq": 144,
      "global_idx": 4312,
      "from_floor": "MT43",
      "to_floor": "MT46",
      "type": "changeFloor",
      "trigger_token": null,
      "waste": 20
    },
    {
      "seq": 145,
      "global_idx": 4313,
      "from_floor": "MT46",
      "to_floor": "MT31",
      "type": "changeFloor",
      "trigger_token": null,
      "waste": 0
    },
    {
      "seq": 146,
      "global_idx": 4336,
      "from_floor": "MT31",
      "to_floor": "MT31",
      "type": "changeFloor",
      "trigger_token": null,
      "waste": 22
    },
    {
      "seq": 147,
      "global_idx": 4337,
      "from_floor": "MT31",
      "to_floor": "MT46",
      "type": "changeFloor",
      "trigger_token": null,
      "waste": 0
    },
    {
      "seq": 148,
      "global_idx": 4368,
      "from_floor": "MT46",
      "to_floor": "MT37",
      "type": "centerFly",
      "trigger_token": "ITEM:50",
      "waste": 15
    },
    {
      "seq": 149,
      "global_idx": 4422,
      "from_floor": "MT37",
      "to_floor": "MT43",
      "type": "changeFloor",
      "trigger_token": null,
      "waste": 30
    },
    {
      "seq": 150,
      "global_idx": 4428,
      "from_floor": "MT43",
      "to_floor": "MT45",
      "type": "changeFloor",
      "trigger_token": null,
      "waste": 5
    },
    {
      "seq": 151,
      "global_idx": 4534,
      "from_floor": "MT45",
      "to_floor": "MT37",
      "type": "keyboard_fly",
      "trigger_token": "UNK:K50",
      "waste": 9
    },
    {
      "seq": 152,
      "global_idx": 4568,
      "from_floor": "MT37",
      "to_floor": "MT48",
      "type": "changeFloor",
      "trigger_token": null,
      "waste": 30
    },
    {
      "seq": 153,
      "global_idx": 4569,
      "from_floor": "MT48",
      "to_floor": "MT47",
      "type": "changeFloor",
      "trigger_token": null,
      "waste": 0
    },
    {
      "seq": 154,
      "global_idx": 4604,
      "from_floor": "MT47",
      "to_floor": "MT42",
      "type": "changeFloor",
      "trigger_token": null,
      "waste": 30
    },
    {
      "seq": 155,
      "global_idx": 4660,
      "from_floor": "MT42",
      "to_floor": "MT41",
      "type": "changeFloor",
      "trigger_token": null,
      "waste": 30
    },
    {
      "seq": 156,
      "global_idx": 4661,
      "from_floor": "MT41",
      "to_floor": "MT41",
      "type": "changeFloor",
      "trigger_token": null,
      "waste": 0
    },
    {
      "seq": 157,
      "global_idx": 4670,
      "from_floor": "MT41",
      "to_floor": "MT46",
      "type": "changeFloor",
      "trigger_token": null,
      "waste": 8
    },
    {
      "seq": 158,
      "global_idx": 4671,
      "from_floor": "MT46",
      "to_floor": "MT47",
      "type": "changeFloor",
      "trigger_token": null,
      "waste": 0
    },
    {
      "seq": 159,
      "global_idx": 4713,
      "from_floor": "MT47",
      "to_floor": "MT41",
      "type": "changeFloor",
      "trigger_token": null,
      "waste": 30
    },
    {
      "seq": 160,
      "global_idx": 4913,
      "from_floor": "MT41",
      "to_floor": "MT41",
      "type": "changeFloor",
      "trigger_token": null,
      "waste": 30
    },
    {
      "seq": 161,
      "global_idx": 4920,
      "from_floor": "MT41",
      "to_floor": "MT1",
      "type": "changeFloor",
      "trigger_token": null,
      "waste": 6
    },
    {
      "seq": 162,
      "global_idx": 4966,
      "from_floor": "MT1",
      "to_floor": "MT3",
      "type": "changeFloor",
      "trigger_token": null,
      "waste": 30
    },
    {
      "seq": 163,
      "global_idx": 4967,
      "from_floor": "MT3",
      "to_floor": "MT4",
      "type": "changeFloor",
      "trigger_token": null,
      "waste": 0
    },
    {
      "seq": 164,
      "global_idx": 5001,
      "from_floor": "MT4",
      "to_floor": "MT5",
      "type": "changeFloor",
      "trigger_token": null,
      "waste": 30
    },
    {
      "seq": 165,
      "global_idx": 5006,
      "from_floor": "MT5",
      "to_floor": "MT6",
      "type": "changeFloor",
      "trigger_token": null,
      "waste": 4
    },
    {
      "seq": 166,
      "global_idx": 5017,
      "from_floor": "MT6",
      "to_floor": "MT4",
      "type": "changeFloor",
      "trigger_token": null,
      "waste": 10
    },
    {
      "seq": 167,
      "global_idx": 5045,
      "from_floor": "MT4",
      "to_floor": "MT7",
      "type": "changeFloor",
      "trigger_token": null,
      "waste": 27
    },
    {
      "seq": 168,
      "global_idx": 5050,
      "from_floor": "MT7",
      "to_floor": "MT8",
      "type": "changeFloor",
      "trigger_token": null,
      "waste": 4
    },
    {
      "seq": 169,
      "global_idx": 5063,
      "from_floor": "MT8",
      "to_floor": "MT9",
      "type": "changeFloor",
      "trigger_token": null,
      "waste": 12
    },
    {
      "seq": 170,
      "global_idx": 5233,
      "from_floor": "MT9",
      "to_floor": "MT19",
      "type": "changeFloor",
      "trigger_token": null,
      "waste": 30
    },
    {
      "seq": 171,
      "global_idx": 5248,
      "from_floor": "MT19",
      "to_floor": "MT31",
      "type": "changeFloor",
      "trigger_token": null,
      "waste": 14
    },
    {
      "seq": 172,
      "global_idx": 5338,
      "from_floor": "MT31",
      "to_floor": "MT38",
      "type": "changeFloor",
      "trigger_token": null,
      "waste": 30
    },
    {
      "seq": 173,
      "global_idx": 5349,
      "from_floor": "MT38",
      "to_floor": "MT39",
      "type": "changeFloor",
      "trigger_token": null,
      "waste": 10
    },
    {
      "seq": 174,
      "global_idx": 5351,
      "from_floor": "MT39",
      "to_floor": "MT40",
      "type": "changeFloor",
      "trigger_token": null,
      "waste": 1
    },
    {
      "seq": 175,
      "global_idx": 5353,
      "from_floor": "MT40",
      "to_floor": "MT46",
      "type": "changeFloor",
      "trigger_token": null,
      "waste": 1
    },
    {
      "seq": 176,
      "global_idx": 5375,
      "from_floor": "MT46",
      "to_floor": "MT48",
      "type": "changeFloor",
      "trigger_token": null,
      "waste": 21
    },
    {
      "seq": 177,
      "global_idx": 5399,
      "from_floor": "MT48",
      "to_floor": "MT47",
      "type": "keyboard_fly",
      "trigger_token": "UNK:K49",
      "waste": 7
    },
    {
      "seq": 178,
      "global_idx": 5406,
      "from_floor": "MT47",
      "to_floor": "MT46",
      "type": "changeFloor",
      "trigger_token": null,
      "waste": 6
    },
    {
      "seq": 179,
      "global_idx": 5409,
      "from_floor": "MT46",
      "to_floor": "MT43",
      "type": "changeFloor",
      "trigger_token": null,
      "waste": 2
    },
    {
      "seq": 180,
      "global_idx": 5449,
      "from_floor": "MT43",
      "to_floor": "MT42",
      "type": "changeFloor",
      "trigger_token": null,
      "waste": 30
    },
    {
      "seq": 181,
      "global_idx": 5466,
      "from_floor": "MT42",
      "to_floor": "MT41",
      "type": "changeFloor",
      "trigger_token": null,
      "waste": 16
    },
    {
      "seq": 182,
      "global_idx": 5468,
      "from_floor": "MT41",
      "to_floor": "MT45",
      "type": "changeFloor",
      "trigger_token": null,
      "waste": 1
    },
    {
      "seq": 183,
      "global_idx": 5469,
      "from_floor": "MT45",
      "to_floor": "MT45",
      "type": "changeFloor",
      "trigger_token": null,
      "waste": 0
    },
    {
      "seq": 184,
      "global_idx": 5490,
      "from_floor": "MT45",
      "to_floor": "MT47",
      "type": "changeFloor",
      "trigger_token": null,
      "waste": 20
    },
    {
      "seq": 185,
      "global_idx": 5492,
      "from_floor": "MT47",
      "to_floor": "MT48",
      "type": "changeFloor",
      "trigger_token": null,
      "waste": 1
    },
    {
      "seq": 186,
      "global_idx": 5518,
      "from_floor": "MT48",
      "to_floor": "MT46",
      "type": "changeFloor",
      "trigger_token": null,
      "waste": 25
    },
    {
      "seq": 187,
      "global_idx": 5531,
      "from_floor": "MT46",
      "to_floor": "MT46",
      "type": "changeFloor",
      "trigger_token": null,
      "waste": 12
    },
    {
      "seq": 188,
      "global_idx": 5550,
      "from_floor": "MT46",
      "to_floor": "MT45",
      "type": "changeFloor",
      "trigger_token": null,
      "waste": 18
    },
    {
      "seq": 189,
      "global_idx": 5568,
      "from_floor": "MT45",
      "to_floor": "MT43",
      "type": "changeFloor",
      "trigger_token": null,
      "waste": 17
    },
    {
      "seq": 190,
      "global_idx": 5613,
      "from_floor": "MT43",
      "to_floor": "MT42",
      "type": "changeFloor",
      "trigger_token": null,
      "waste": 30
    },
    {
      "seq": 191,
      "global_idx": 5617,
      "from_floor": "MT42",
      "to_floor": "MT41",
      "type": "changeFloor",
      "trigger_token": null,
      "waste": 3
    },
    {
      "seq": 192,
      "global_idx": 5621,
      "from_floor": "MT41",
      "to_floor": "MT48",
      "type": "changeFloor",
      "trigger_token": null,
      "waste": 3
    },
    {
      "seq": 193,
      "global_idx": 5681,
      "from_floor": "MT48",
      "to_floor": "MT47",
      "type": "changeFloor",
      "trigger_token": null,
      "waste": 30
    },
    {
      "seq": 194,
      "global_idx": 5740,
      "from_floor": "MT47",
      "to_floor": "MT47",
      "type": "changeFloor",
      "trigger_token": null,
      "waste": 30
    },
    {
      "seq": 195,
      "global_idx": 5762,
      "from_floor": "MT47",
      "to_floor": "MT45",
      "type": "changeFloor",
      "trigger_token": null,
      "waste": 21
    },
    {
      "seq": 196,
      "global_idx": 5763,
      "from_floor": "MT45",
      "to_floor": "MT49",
      "type": "changeFloor",
      "trigger_token": null,
      "waste": 0
    },
    {
      "seq": 197,
      "global_idx": 5764,
      "from_floor": "MT49",
      "to_floor": "MT49",
      "type": "changeFloor",
      "trigger_token": null,
      "waste": 0
    },
    {
      "seq": 198,
      "global_idx": 5765,
      "from_floor": "MT49",
      "to_floor": "MT42",
      "type": "changeFloor",
      "trigger_token": null,
      "waste": 0
    },
    {
      "seq": 199,
      "global_idx": 5791,
      "from_floor": "MT42",
      "to_floor": "MT49",
      "type": "changeFloor",
      "trigger_token": null,
      "waste": 25
    },
    {
      "seq": 200,
      "global_idx": 5840,
      "from_floor": "MT49",
      "to_floor": "MT46",
      "type": "changeFloor",
      "trigger_token": null,
      "waste": 30
    },
    {
      "seq": 201,
      "global_idx": 5869,
      "from_floor": "MT46",
      "to_floor": "MT45",
      "type": "changeFloor",
      "trigger_token": null,
      "waste": 28
    },
    {
      "seq": 202,
      "global_idx": 5903,
      "from_floor": "MT45",
      "to_floor": "MT45",
      "type": "changeFloor",
      "trigger_token": null,
      "waste": 30
    },
    {
      "seq": 203,
      "global_idx": 5909,
      "from_floor": "MT45",
      "to_floor": "MT35",
      "type": "changeFloor",
      "trigger_token": null,
      "waste": 5
    },
    {
      "seq": 204,
      "global_idx": 5910,
      "from_floor": "MT35",
      "to_floor": "MT35",
      "type": "changeFloor",
      "trigger_token": null,
      "waste": 0
    },
    {
      "seq": 205,
      "global_idx": 5922,
      "from_floor": "MT35",
      "to_floor": "MT13",
      "type": "changeFloor",
      "trigger_token": null,
      "waste": 11
    },
    {
      "seq": 206,
      "global_idx": 6014,
      "from_floor": "MT13",
      "to_floor": "MT43",
      "type": "changeFloor",
      "trigger_token": null,
      "waste": 30
    },
    {
      "seq": 207,
      "global_idx": 6068,
      "from_floor": "MT43",
      "to_floor": "MT41",
      "type": "changeFloor",
      "trigger_token": null,
      "waste": 30
    },
    {
      "seq": 208,
      "global_idx": 6069,
      "from_floor": "MT41",
      "to_floor": "MT41",
      "type": "changeFloor",
      "trigger_token": null,
      "waste": 0
    },
    {
      "seq": 209,
      "global_idx": 6072,
      "from_floor": "MT41",
      "to_floor": "MT45",
      "type": "changeFloor",
      "trigger_token": null,
      "waste": 2
    },
    {
      "seq": 210,
      "global_idx": 6133,
      "from_floor": "MT45",
      "to_floor": "MT45",
      "type": "changeFloor",
      "trigger_token": null,
      "waste": 30
    },
    {
      "seq": 211,
      "global_idx": 6140,
      "from_floor": "MT45",
      "to_floor": "MT48",
      "type": "changeFloor",
      "trigger_token": null,
      "waste": 6
    },
    {
      "seq": 212,
      "global_idx": 6172,
      "from_floor": "MT48",
      "to_floor": "MT20",
      "type": "changeFloor",
      "trigger_token": null,
      "waste": 30
    },
    {
      "seq": 213,
      "global_idx": 6173,
      "from_floor": "MT20",
      "to_floor": "MT20",
      "type": "changeFloor",
      "trigger_token": null,
      "waste": 0
    },
    {
      "seq": 214,
      "global_idx": 6197,
      "from_floor": "MT20",
      "to_floor": "MT25",
      "type": "changeFloor",
      "trigger_token": null,
      "waste": 23
    },
    {
      "seq": 215,
      "global_idx": 6210,
      "from_floor": "MT25",
      "to_floor": "MT2",
      "type": "changeFloor",
      "trigger_token": null,
      "waste": 12
    },
    {
      "seq": 216,
      "global_idx": 6240,
      "from_floor": "MT2",
      "to_floor": "MT25",
      "type": "changeFloor",
      "trigger_token": null,
      "waste": 29
    },
    {
      "seq": 217,
      "global_idx": 6259,
      "from_floor": "MT25",
      "to_floor": "MT26",
      "type": "changeFloor",
      "trigger_token": null,
      "waste": 18
    },
    {
      "seq": 218,
      "global_idx": 6326,
      "from_floor": "MT26",
      "to_floor": "MT12",
      "type": "changeFloor",
      "trigger_token": null,
      "waste": 30
    },
    {
      "seq": 219,
      "global_idx": 6347,
      "from_floor": "MT12",
      "to_floor": "MT24",
      "type": "changeFloor",
      "trigger_token": null,
      "waste": 20
    }
  ]
}